hotel_elasticsearch/__init__.py
hotel_elasticsearch/alerting.py
hotel_elasticsearch/app.py
hotel_elasticsearch/aws_utils.py
hotel_elasticsearch/backup.py
hotel_elasticsearch/clusternode.py
hotel_elasticsearch/configuration.py
hotel_elasticsearch/monitoring.py
hotel_elasticsearch/service.py
hotel_elasticsearch-2.0.0.dist-info/METADATA
hotel_elasticsearch-2.0.0.dist-info/WHEEL
hotel_elasticsearch-2.0.0.dist-info/entry_points.txt
hotel_elasticsearch-2.0.0.dist-info/top_level.txt
hotel_elasticsearch-2.0.0.dist-info/RECORD
