Metadata-Version: 2.1
Name: hotel-elasticsearch
Version: 2.0.0
Home-page: 
Author: Kristian Øllegaard
Author-email: kristian@plecto.com
Requires-Dist: PyYAML
Requires-Dist: boto3
Requires-Dist: requests
Requires-Dist: frigga-snake
Requires-Dist: aws-secretsmanager-caching
